machinery/__init__.py
machinery/api.py
workflow_machinery-0.0.0.dist-info/METADATA
workflow_machinery-0.0.0.dist-info/WHEEL
workflow_machinery-0.0.0.dist-info/top_level.txt
workflow_machinery-0.0.0.dist-info/RECORD
